pytest_fastcollect-0.5.0.dist-info/METADATA
pytest_fastcollect-0.5.0.dist-info/WHEEL
pytest_fastcollect-0.5.0.dist-info/entry_points.txt
pytest_fastcollect-0.5.0.dist-info/licenses/LICENSE
pytest_fastcollect.libs/libgcc_s-27e5a392.so.1
pytest_fastcollect/__init__.py
pytest_fastcollect/cache.py
pytest_fastcollect/daemon.py
pytest_fastcollect/daemon_client.py
pytest_fastcollect/filter.py
pytest_fastcollect/plugin.py
pytest_fastcollect/pytest_fastcollect.cpython-312-i386-linux-musl.so
pytest_fastcollect/socket_strategy.py
pytest_fastcollect-0.5.0.dist-info/RECORD
