Metadata-Version: 2.4
Name: pytest-fastcollect
Version: 0.5.0
Classifier: Framework :: Pytest
Classifier: Programming Language :: Rust
Classifier: Programming Language :: Python :: Implementation :: CPython
Classifier: Programming Language :: Python :: Implementation :: PyPy
Classifier: Topic :: Software Development :: Testing
Requires-Dist: pytest>=7.0.0
Requires-Dist: pytest-benchmark>=4.0.0 ; extra == 'dev'
Provides-Extra: dev
License-File: LICENSE
Summary: A high-performance pytest plugin that replaces test collection with a Rust-based implementation
Requires-Python: >=3.8
